cleaner/__init__.py
cleaner/__main__.py
cleaner/git_repo_cleaner.py
cleaner/__pycache__/__init__.cpython-310.pyc
cleaner/__pycache__/__init__.cpython-39.pyc
cleaner/__pycache__/__main__.cpython-310.pyc
cleaner/__pycache__/__main__.cpython-39.pyc
cleaner/__pycache__/git_repo_cleaner.cpython-310.pyc
git_branch_cleaner-1.2.0.dist-info/LICENSE
git_branch_cleaner-1.2.0.dist-info/METADATA
git_branch_cleaner-1.2.0.dist-info/WHEEL
git_branch_cleaner-1.2.0.dist-info/entry_points.txt
git_branch_cleaner-1.2.0.dist-info/top_level.txt
git_branch_cleaner-1.2.0.dist-info/RECORD
