Metadata-Version: 2.1
Name: git-branch-cleaner
Version: 1.2.0
Summary: Connect to git repository and delete branches which are not in remote repository from local repository
Author-email: Vishnu Gangadhara Naik <vishnugnaik@gmail.com>
License: MIT License
Project-URL: repository, https://github.com/Vishnu-Naik/git-branch-cleaner
Keywords: git,branches,delete
Classifier: License :: OSI Approved :: MIT License
Classifier: Programming Language :: Python
Classifier: Programming Language :: Python :: 3.10
Requires-Python: >=3.10
License-File: LICENSE
Requires-Dist: GitPython (>=3.1.30)
